pipbuilder/__init__.py
pipbuilder/__main__.py
pipbuilder/pipbuilder.py
pipbuilder-1.0.0.dist-info/LICENSE
pipbuilder-1.0.0.dist-info/METADATA
pipbuilder-1.0.0.dist-info/WHEEL
pipbuilder-1.0.0.dist-info/top_level.txt
pipbuilder-1.0.0.dist-info/RECORD
