Metadata-Version: 2.1
Name: pipbuilder
Version: 1.0.0
Summary: Python PIP Package Builder
Home-page: https://github.com/YELANDAOKONG/pipbuilder
Author: YELANDAOKONG
Author-email: YELANDAOKONG@yldk.xyz
Classifier: Programming Language :: Python :: 3
Classifier: License :: OSI Approved :: MIT License
Classifier: Operating System :: OS Independent
Requires-Python: >=3.6
License-File: LICENSE
